cryptlib/__init__.py
cryptlib/encstr.py
cryptlib-0.0.4.dist-info/LICENSE
cryptlib-0.0.4.dist-info/METADATA
cryptlib-0.0.4.dist-info/WHEEL
cryptlib-0.0.4.dist-info/top_level.txt
cryptlib-0.0.4.dist-info/RECORD
