Metadata-Version: 2.1
Name: cryptlib
Version: 0.0.4
Summary: python string encryption using multiple techniques
Home-page: https://github.com/Falldog/pyconcrete
Author: James root
Author-email: falldog7@gmail.com
Classifier: Programming Language :: Python :: 3
Classifier: License :: OSI Approved :: MIT License
Classifier: Operating System :: OS Independent
Requires-Python: >=3.7
License-File: LICENSE
